{
    "AX": {
        "error": 0.010169631208577126, 
        "filter_outliers_dict": {
            "filter_outliers": true, 
            "iterations": 1, 
            "std_devs": 2
        }, 
        "fit": "average", 
        "value": -0.11029507027152409
    }, 
    "H1": {
        "error": 0.012141371492938157, 
        "filter_outliers_dict": {
            "filter_outliers": true, 
            "iterations": 1, 
            "std_devs": 2
        }, 
        "fit": "average", 
        "value": -0.05677405710965012
    }, 
    "H2": {
        "error": 0.010593445676489377, 
        "filter_outliers_dict": {
            "filter_outliers": true, 
            "iterations": 1, 
            "std_devs": 2
        }, 
        "fit": "average", 
        "value": 0.0799518732296995
    }, 
    "L1": {
        "error": 0.008919243379312578, 
        "filter_outliers_dict": {
            "filter_outliers": true, 
            "iterations": 1, 
            "std_devs": 2
        }, 
        "fit": "average", 
        "value": 0.011596099725587899
    }, 
    "L2(CDD)": {
        "error": 9.775818662133737e-06, 
        "filter_outliers_dict": {
            "filter_outliers": true, 
            "iterations": 1, 
            "std_devs": 2
        }, 
        "fit": "average", 
        "value": 9.10364048296966e-05
    }
}