{
    "AX": {
        "error": 0.009315086768444388, 
        "filter_outliers_dict": {
            "filter_outliers": true, 
            "iterations": 1, 
            "std_devs": 2
        }, 
        "fit": "average", 
        "value": -0.12760948236973943
    }, 
    "H1": {
        "error": 0.011145743599803767, 
        "filter_outliers_dict": {
            "filter_outliers": true, 
            "iterations": 1, 
            "std_devs": 2
        }, 
        "fit": "average", 
        "value": -0.016274474952323335
    }, 
    "H2": {
        "error": 0.009770033414697685, 
        "filter_outliers_dict": {
            "filter_outliers": true, 
            "iterations": 1, 
            "std_devs": 2
        }, 
        "fit": "average", 
        "value": 0.083206184702204
    }, 
    "L1": {
        "error": 0.009200530138469252, 
        "filter_outliers_dict": {
            "filter_outliers": true, 
            "iterations": 1, 
            "std_devs": 2
        }, 
        "fit": "average", 
        "value": -0.008370982552856385
    }, 
    "L2(CDD)": {
        "error": 1.1378024793626603e-05, 
        "filter_outliers_dict": {
            "filter_outliers": true, 
            "iterations": 1, 
            "std_devs": 2
        }, 
        "fit": "average", 
        "value": 0.0001117264972836957
    }
}