{
    "Ar36": {
        "error": 0.0035691609426844956, 
        "filter_outliers_dict": {
            "filter_outliers": true, 
            "iterations": 2, 
            "std_devs": 2
        }, 
        "fit": "Parabolic", 
        "value": 3.3471243610674675
    }, 
    "Ar37": {
        "error": 0.011546507463693697, 
        "filter_outliers_dict": {
            "filter_outliers": true, 
            "iterations": 2, 
            "std_devs": 2
        }, 
        "fit": "linear", 
        "value": 0.02248653672273564
    }, 
    "Ar38": {
        "error": 0.012814230644128668, 
        "filter_outliers_dict": {
            "filter_outliers": true, 
            "iterations": 2, 
            "std_devs": 2
        }, 
        "fit": "linear", 
        "value": 0.5261818712484203
    }, 
    "Ar39": {
        "error": 0.022189049901445657, 
        "filter_outliers_dict": {
            "filter_outliers": true, 
            "iterations": 2, 
            "std_devs": 2
        }, 
        "fit": "Parabolic", 
        "value": -0.0689109156414947
    }, 
    "Ar40": {
        "error": 0.06118570179297679, 
        "filter_outliers_dict": {
            "filter_outliers": true, 
            "iterations": 2, 
            "std_devs": 2
        }, 
        "fit": "Parabolic", 
        "value": 996.1921520981978
    }
}